{
  "day": 28,
  "entries": {
    "uAZsq7NTsCQ03Xm": {
      "name": "Anyelo",
      "char": 2,
      "skin": false,
      "area": 1,
      "subarea": 1,
      "loops": 0,
      "wep": 19,
      "bwep": 1,
      "win": false,
      "kills": 9,
      "crown": 1,
      "version": 2616,
      "uid": "uAZsq7NTsCQ03Xm",
      "runId": 801681773
    },
    "45s1v1MwMCaw7mY": {
      "name": "REFT532",
      "char": 3,
      "skin": false,
      "area": 2,
      "subarea": 1,
      "loops": 0,
      "wep": 5,
      "bwep": 2,
      "win": false,
      "kills": 65,
      "ultra": 0,
      "skills": [
        4,
        19
      ],
      "crown": 1,
      "version": 2616,
      "uid": "45s1v1MwMCaw7mY",
      "runId": 801681773
    },
    "wcX8m72OsiDi49E": {
      "name": "tio7roberto",
      "char": 4,
      "skin": false,
      "area": 1,
      "subarea": 1,
      "loops": 0,
      "wep": 3,
      "bwep": 1,
      "win": false,
      "kills": 0,
      "crown": 1,
      "version": 2616,
      "uid": "wcX8m72OsiDi49E",
      "runId": 801681773
    },
    "559m20TnnPeI646": {
      "name": "DuckGhost732",
      "char": 4,
      "skin": false,
      "area": 5,
      "subarea": 3,
      "loops": 0,
      "wep": 84,
      "bwep": 66,
      "win": false,
      "kills": 273,
      "ultra": 0,
      "skills": [
        10,
        27,
        14,
        22
      ],
      "crown": 10,
      "version": 2616,
      "uid": "559m20TnnPeI646",
      "runId": 801681773
    },
    "P4x8JbsY7V8fl5A": {
      "name": "hoiisa",
      "char": 1,
      "skin": false,
      "area": 1,
      "subarea": 1,
      "loops": 0,
      "wep": 5,
      "bwep": 1,
      "win": false,
      "kills": 7,
      "crown": 1,
      "version": 2616,
      "uid": "P4x8JbsY7V8fl5A",
      "runId": 801681773
    },
    "48Hj07E8MEmLwZb": {
      "name": "Seeker51222",
      "char": 8,
      "skin": false,
      "area": 1,
      "subarea": 2,
      "loops": 0,
      "wep": 5,
      "bwep": 6,
      "win": false,
      "kills": 18,
      "ultra": 0,
      "skills": [
        26
      ],
      "crown": 1,
      "version": 2616,
      "uid": "48Hj07E8MEmLwZb",
      "runId": 801681773
    }
  }
}