{
  "day": 15,
  "entries": {
    "ckSD2t2wYgR9J7N": {
      "name": "Hy",
      "char": 2,
      "skin": false,
      "area": 1,
      "subarea": 2,
      "loops": 0,
      "wep": 7,
      "bwep": 1,
      "win": false,
      "kills": 8,
      "crown": 1,
      "version": 2616,
      "uid": "ckSD2t2wYgR9J7N",
      "runId": 238269113
    },
    "Ifdjsv6cZ47XJzs": {
      "name": "gantzin",
      "char": 12,
      "skin": false,
      "area": 1,
      "subarea": 1,
      "loops": 0,
      "wep": 81,
      "bwep": 0,
      "win": false,
      "kills": 0,
      "crown": 1,
      "version": 2616,
      "uid": "Ifdjsv6cZ47XJzs",
      "runId": 238269113
    },
    "lGocB90tI2e8ZEB": {
      "name": "foopa",
      "char": 1,
      "skin": false,
      "area": 1,
      "subarea": 3,
      "loops": 0,
      "wep": 7,
      "bwep": 1,
      "win": false,
      "kills": 26,
      "ultra": 0,
      "skills": [
        27
      ],
      "crown": 1,
      "version": 2616,
      "uid": "lGocB90tI2e8ZEB",
      "runId": 238269113
    },
    "7C7UIq3Dr1Dh51n": {
      "name": "brazzer250",
      "char": 10,
      "skin": false,
      "area": 5,
      "subarea": 1,
      "loops": 0,
      "wep": 76,
      "bwep": 26,
      "win": false,
      "kills": 178,
      "ultra": 0,
      "skills": [
        8,
        4,
        21,
        1
      ],
      "crown": 4,
      "version": 2616,
      "uid": "7C7UIq3Dr1Dh51n",
      "runId": 238269113
    },
    "WoxUmfP37M78eln": {
      "name": "YES_KING",
      "char": 4,
      "skin": false,
      "area": 2,
      "subarea": 1,
      "loops": 0,
      "wep": 17,
      "bwep": 5,
      "win": false,
      "kills": 42,
      "ultra": 0,
      "skills": [
        27,
        4
      ],
      "crown": 1,
      "version": 2616,
      "uid": "WoxUmfP37M78eln",
      "runId": 238269113
    }
  }
}