{
  "day": 29,
  "entries": {
    "23qMNVFxOgW28dk": {
      "name": "tu",
      "char": 2,
      "skin": false,
      "area": 4,
      "subarea": 1,
      "loops": 0,
      "wep": 13,
      "bwep": 21,
      "win": false,
      "kills": 56,
      "ultra": 0,
      "skills": [
        12
      ],
      "crown": 1,
      "version": 2616,
      "uid": "23qMNVFxOgW28dk",
      "runId": 976729719
    },
    "G026mmme6btK3Ik": {
      "name": "pauldo",
      "char": 2,
      "skin": false,
      "area": 1,
      "subarea": 3,
      "loops": 0,
      "wep": 1,
      "bwep": 0,
      "win": false,
      "kills": 19,
      "ultra": 0,
      "skills": [],
      "crown": 1,
      "version": 2616,
      "uid": "G026mmme6btK3Ik",
      "runId": 976729719
    },
    "7b5OiM785GhH29Z": {
      "name": "EDERZON",
      "char": 7,
      "skin": false,
      "area": 1,
      "subarea": 3,
      "loops": 0,
      "wep": 3,
      "bwep": 1,
      "win": false,
      "kills": 36,
      "ultra": 0,
      "skills": [],
      "crown": 1,
      "version": 2616,
      "uid": "7b5OiM785GhH29Z",
      "runId": 976729719
    },
    "262G2AK6i2cKa4P": {
      "name": "GAYDOANAL",
      "char": 8,
      "skin": true,
      "area": 4,
      "subarea": 1,
      "loops": 0,
      "wep": 38,
      "bwep": 1,
      "win": false,
      "kills": 140,
      "ultra": 0,
      "skills": [
        24,
        3,
        10
      ],
      "crown": 1,
      "version": 2616,
      "uid": "262G2AK6i2cKa4P",
      "runId": 976729719
    },
    "n5BA29aG845IhTO": {
      "name": "челик",
      "char": 8,
      "skin": true,
      "area": 5,
      "subarea": 3,
      "loops": 0,
      "wep": 91,
      "bwep": 52,
      "win": false,
      "kills": 233,
      "ultra": 0,
      "skills": [
        13,
        12,
        1,
        27,
        22,
        6
      ],
      "crown": 1,
      "version": 2616,
      "uid": "n5BA29aG845IhTO",
      "runId": 976729719
    },
    "892Y5ozZ0h8r0Kq": {
      "name": "Natsume",
      "char": 8,
      "skin": true,
      "area": 3,
      "subarea": 1,
      "loops": 0,
      "wep": 3,
      "bwep": 1,
      "win": false,
      "kills": 67,
      "ultra": 0,
      "skills": [
        12
      ],
      "crown": 1,
      "version": 2616,
      "uid": "892Y5ozZ0h8r0Kq",
      "runId": 976729719
    },
    "y83Nw12V5Zyxof5": {
      "name": "bruhhehe",
      "char": 3,
      "skin": false,
      "area": 5,
      "subarea": 3,
      "loops": 0,
      "wep": 63,
      "bwep": 38,
      "win": false,
      "kills": 238,
      "ultra": 0,
      "skills": [
        12,
        1,
        10,
        26,
        6
      ],
      "crown": 1,
      "version": 2616,
      "uid": "y83Nw12V5Zyxof5",
      "runId": 976729719
    },
    "Qt41JaCbwVJ1bvV": {
      "name": "gucciTRAPS",
      "char": 2,
      "skin": false,
      "area": 3,
      "subarea": 1,
      "loops": 0,
      "wep": 69,
      "bwep": 16,
      "win": false,
      "kills": 74,
      "ultra": 0,
      "skills": [
        26
      ],
      "crown": 1,
      "version": 2616,
      "uid": "Qt41JaCbwVJ1bvV",
      "runId": 976729719
    },
    "gE8H8OQcl1q7D57": {
      "name": "MaybeD",
      "char": 7,
      "skin": false,
      "area": 1,
      "subarea": 3,
      "loops": 0,
      "wep": 1,
      "bwep": 1,
      "win": false,
      "kills": 34,
      "ultra": 0,
      "skills": [
        17
      ],
      "crown": 1,
      "version": 2616,
      "uid": "gE8H8OQcl1q7D57",
      "runId": 976729719
    },
    "64lsh4Hwg4ysAv1": {
      "name": "Kenned",
      "char": 8,
      "skin": true,
      "area": 3,
      "subarea": 2,
      "loops": 0,
      "wep": 3,
      "bwep": 69,
      "win": false,
      "kills": 93,
      "ultra": 0,
      "skills": [
        12,
        1
      ],
      "crown": 1,
      "version": 2616,
      "uid": "64lsh4Hwg4ysAv1",
      "runId": 976729719
    },
    "Q3An8fn5Wyc5pXq": {
      "name": "хуй",
      "char": 2,
      "skin": true,
      "area": 1,
      "subarea": 1,
      "loops": 1,
      "wep": 91,
      "bwep": 60,
      "win": false,
      "kills": 385,
      "ultra": 2,
      "skills": [
        17,
        12,
        1,
        27,
        2,
        10,
        8,
        13
      ],
      "crown": 1,
      "version": 2616,
      "uid": "Q3An8fn5Wyc5pXq",
      "runId": 976729719
    },
    "fdzh6G8dKtuY12H": {
      "name": "Marky",
      "char": 1,
      "skin": false,
      "area": 1,
      "subarea": 3,
      "loops": 0,
      "wep": 3,
      "bwep": 1,
      "win": false,
      "kills": 27,
      "ultra": 0,
      "skills": [],
      "crown": 1,
      "version": 2616,
      "uid": "fdzh6G8dKtuY12H",
      "runId": 976729719
    },
    "nS4tAXaS957Jv42": {
      "name": "korin",
      "char": 8,
      "skin": false,
      "area": 1,
      "subarea": 3,
      "loops": 0,
      "wep": 71,
      "bwep": 3,
      "win": false,
      "kills": 34,
      "ultra": 0,
      "skills": [
        17
      ],
      "crown": 1,
      "version": 2616,
      "uid": "nS4tAXaS957Jv42",
      "runId": 976729719
    },
    "6YftXcX8qWEOLSn": {
      "name": "Wawita",
      "char": 1,
      "skin": false,
      "area": 1,
      "subarea": 3,
      "loops": 0,
      "wep": 1,
      "bwep": 27,
      "win": false,
      "kills": 33,
      "ultra": 0,
      "skills": [
        17
      ],
      "crown": 1,
      "version": 2616,
      "uid": "6YftXcX8qWEOLSn",
      "runId": 976729719
    },
    "W471611Hz3mp7zD": {
      "name": "xxx",
      "char": 1,
      "skin": false,
      "area": 1,
      "subarea": 3,
      "loops": 0,
      "wep": 19,
      "bwep": 1,
      "win": false,
      "kills": 39,
      "ultra": 0,
      "skills": [],
      "crown": 1,
      "version": 2616,
      "uid": "W471611Hz3mp7zD",
      "runId": 976729719
    },
    "Rjgbeq4u87m9fox": {
      "name": "See",
      "char": 2,
      "skin": true,
      "area": 3,
      "subarea": 3,
      "loops": 0,
      "wep": 41,
      "bwep": 50,
      "win": false,
      "kills": 120,
      "ultra": 0,
      "skills": [
        13,
        26,
        1
      ],
      "crown": 1,
      "version": 2616,
      "uid": "Rjgbeq4u87m9fox",
      "runId": 976729719
    },
    "U48H0F3Z26SizMo": {
      "name": "SamRye",
      "char": 5,
      "skin": false,
      "area": 1,
      "subarea": 3,
      "loops": 0,
      "wep": 69,
      "bwep": 27,
      "win": false,
      "kills": 41,
      "ultra": 0,
      "skills": [],
      "crown": 1,
      "version": 2616,
      "uid": "U48H0F3Z26SizMo",
      "runId": 976729719
    },
    "fw5S1UfnhkI086O": {
      "name": "Brzxo",
      "char": 2,
      "skin": true,
      "area": 0,
      "subarea": 1,
      "loops": 1,
      "wep": 60,
      "bwep": 57,
      "win": false,
      "kills": 334,
      "ultra": 1,
      "skills": [
        17,
        23,
        1,
        27,
        22,
        25,
        8,
        4,
        10
      ],
      "crown": 11,
      "version": 2616,
      "uid": "fw5S1UfnhkI086O",
      "runId": 976729719
    },
    "xnI677V5k9292b3": {
      "name": "BlackGamer389",
      "char": 7,
      "skin": false,
      "area": 103,
      "subarea": 1,
      "loops": 0,
      "wep": 27,
      "bwep": 1,
      "win": false,
      "kills": 110,
      "ultra": 0,
      "skills": [
        12,
        1
      ],
      "crown": 1,
      "version": 2616,
      "uid": "xnI677V5k9292b3",
      "runId": 976729719
    },
    "XUQ178r3zG82nn9": {
      "name": "BubaSlon",
      "char": 8,
      "skin": true,
      "area": 3,
      "subarea": 3,
      "loops": 0,
      "wep": 9,
      "bwep": 38,
      "win": false,
      "kills": 111,
      "ultra": 0,
      "skills": [
        17,
        23,
        3
      ],
      "crown": 1,
      "version": 2616,
      "uid": "XUQ178r3zG82nn9",
      "runId": 976729719
    },
    "Is5F2iVekK2V7O8": {
      "name": "El",
      "char": 4,
      "skin": true,
      "area": 2,
      "subarea": 1,
      "loops": 0,
      "wep": 19,
      "bwep": 3,
      "win": false,
      "kills": 50,
      "ultra": 0,
      "skills": [
        13,
        12
      ],
      "crown": 1,
      "version": 2616,
      "uid": "Is5F2iVekK2V7O8",
      "runId": 976729719
    },
    "W1kH7AFDp89wu9N": {
      "name": "bathroombully",
      "char": 3,
      "skin": false,
      "area": 3,
      "subarea": 1,
      "loops": 0,
      "wep": 69,
      "bwep": 50,
      "win": false,
      "kills": 74,
      "ultra": 0,
      "skills": [
        12
      ],
      "crown": 1,
      "version": 2616,
      "uid": "W1kH7AFDp89wu9N",
      "runId": 976729719
    },
    "mt3lMgn6HRLT48k": {
      "name": "INFy",
      "char": 2,
      "skin": false,
      "area": 1,
      "subarea": 3,
      "loops": 0,
      "wep": 21,
      "bwep": 27,
      "win": false,
      "kills": 39,
      "ultra": 0,
      "skills": [
        17
      ],
      "crown": 1,
      "version": 2616,
      "uid": "mt3lMgn6HRLT48k",
      "runId": 976729719
    },
    "HPq07AWj6MWLWQw": {
      "name": "STRVACT",
      "char": 4,
      "skin": true,
      "area": 3,
      "subarea": 1,
      "loops": 0,
      "wep": 3,
      "bwep": 27,
      "win": false,
      "kills": 67,
      "ultra": 0,
      "skills": [
        13,
        23,
        1
      ],
      "crown": 1,
      "version": 2616,
      "uid": "HPq07AWj6MWLWQw",
      "runId": 976729719
    },
    "pmOQ5Usk7hul3BE": {
      "name": "Seewkwjsnskdk",
      "char": 6,
      "skin": true,
      "area": 3,
      "subarea": 3,
      "loops": 0,
      "wep": 13,
      "bwep": 76,
      "win": false,
      "kills": 116,
      "ultra": 0,
      "skills": [
        13,
        23,
        1
      ],
      "crown": 1,
      "version": 2616,
      "uid": "pmOQ5Usk7hul3BE",
      "runId": 976729719
    }
  }
}