{
  "day": 13,
  "entries": {
    "m3Ghf170HISs120": {
      "name": "Thwelnwzaaa",
      "char": 2,
      "skin": true,
      "area": 3,
      "subarea": 2,
      "loops": 0,
      "wep": 21,
      "bwep": 69,
      "win": false,
      "kills": 95,
      "ultra": 0,
      "skills": [
        2,
        8,
        4
      ],
      "crown": 1,
      "version": 2616,
      "uid": "m3Ghf170HISs120",
      "runId": 663081683
    },
    "PMQlYcaD202tZmI": {
      "name": "tsun444",
      "char": 1,
      "skin": false,
      "area": 3,
      "subarea": 3,
      "loops": 0,
      "wep": 17,
      "bwep": 31,
      "win": false,
      "kills": 125,
      "ultra": 0,
      "skills": [
        8,
        12
      ],
      "crown": 4,
      "version": 2616,
      "uid": "PMQlYcaD202tZmI",
      "runId": 663081683
    },
    "s4HD8UF9YlocVKg": {
      "name": "dan",
      "char": 2,
      "skin": false,
      "area": 2,
      "subarea": 1,
      "loops": 0,
      "wep": 13,
      "bwep": 1,
      "win": false,
      "kills": 51,
      "ultra": 0,
      "skills": [
        2,
        8
      ],
      "crown": 1,
      "version": 2616,
      "uid": "s4HD8UF9YlocVKg",
      "runId": 663081683
    },
    "lC4sZC8L81G8Hb8": {
      "name": "ILoveMyWife",
      "char": 10,
      "skin": true,
      "area": 100,
      "subarea": 1,
      "loops": 0,
      "wep": 12,
      "bwep": 9,
      "win": false,
      "kills": 222,
      "ultra": 0,
      "skills": [
        25,
        7,
        9,
        4,
        24,
        3,
        1
      ],
      "crown": 4,
      "version": 2616,
      "uid": "lC4sZC8L81G8Hb8",
      "runId": 663081683
    },
    "3C9hOmwuuEC8QQE": {
      "name": "munoo",
      "char": 3,
      "skin": true,
      "area": 3,
      "subarea": 2,
      "loops": 0,
      "wep": 13,
      "bwep": 21,
      "win": false,
      "kills": 100,
      "ultra": 0,
      "skills": [
        9,
        4
      ],
      "crown": 1,
      "version": 2616,
      "uid": "3C9hOmwuuEC8QQE",
      "runId": 663081683
    },
    "S2s15c61DM7441x": {
      "name": "tico",
      "char": 2,
      "skin": false,
      "area": 3,
      "subarea": 2,
      "loops": 0,
      "wep": 13,
      "bwep": 61,
      "win": false,
      "kills": 102,
      "ultra": 0,
      "skills": [
        26
      ],
      "crown": 1,
      "version": 2616,
      "uid": "S2s15c61DM7441x",
      "runId": 663081683
    },
    "qA5z1173O86HB9U": {
      "name": "LOKAKO",
      "char": 2,
      "skin": false,
      "area": 7,
      "subarea": 3,
      "loops": 0,
      "wep": 66,
      "bwep": 58,
      "win": false,
      "kills": 346,
      "ultra": 0,
      "skills": [
        8,
        10,
        4,
        22,
        7
      ],
      "crown": 4,
      "version": 2616,
      "uid": "qA5z1173O86HB9U",
      "runId": 663081683
    },
    "E79S7536XzjeG0K": {
      "name": "Elpepe123_67",
      "char": 2,
      "skin": true,
      "area": 3,
      "subarea": 2,
      "loops": 0,
      "wep": 13,
      "bwep": 61,
      "win": false,
      "kills": 88,
      "ultra": 0,
      "skills": [
        8,
        26
      ],
      "crown": 1,
      "version": 2616,
      "uid": "E79S7536XzjeG0K",
      "runId": 663081683
    },
    "q4v53225od1tbzy": {
      "name": "J",
      "char": 2,
      "skin": false,
      "area": 1,
      "subarea": 3,
      "loops": 0,
      "wep": 13,
      "bwep": 21,
      "win": false,
      "kills": 45,
      "ultra": 0,
      "skills": [],
      "crown": 1,
      "version": 2616,
      "uid": "q4v53225od1tbzy",
      "runId": 663081683
    },
    "8Cb00P2oi49tP79": {
      "name": "max",
      "char": 4,
      "skin": false,
      "area": 3,
      "subarea": 1,
      "loops": 0,
      "wep": 21,
      "bwep": 4,
      "win": false,
      "kills": 84,
      "ultra": 0,
      "skills": [
        8,
        4
      ],
      "crown": 1,
      "version": 2616,
      "uid": "8Cb00P2oi49tP79",
      "runId": 663081683
    },
    "QCuF3Tq0085A195": {
      "name": "cavees",
      "char": 7,
      "skin": false,
      "area": 3,
      "subarea": 1,
      "loops": 0,
      "wep": 13,
      "bwep": 1,
      "win": false,
      "kills": 66,
      "ultra": 0,
      "skills": [
        9,
        4
      ],
      "crown": 1,
      "version": 2616,
      "uid": "QCuF3Tq0085A195",
      "runId": 663081683
    },
    "W36AYDnfg5H5mwJ": {
      "name": "3ds",
      "char": 12,
      "skin": false,
      "area": 3,
      "subarea": 1,
      "loops": 0,
      "wep": 17,
      "bwep": 3,
      "win": false,
      "kills": 90,
      "ultra": 0,
      "skills": [
        9
      ],
      "crown": 1,
      "version": 2616,
      "uid": "W36AYDnfg5H5mwJ",
      "runId": 663081683
    },
    "kCYSmJ6emz05igU": {
      "name": "Meleemoose",
      "char": 2,
      "skin": false,
      "area": 3,
      "subarea": 1,
      "loops": 0,
      "wep": 21,
      "bwep": 1,
      "win": false,
      "kills": 67,
      "ultra": 0,
      "skills": [
        8
      ],
      "crown": 1,
      "version": 2616,
      "uid": "kCYSmJ6emz05igU",
      "runId": 663081683
    },
    "wMoFZw0K728rw20": {
      "name": "Jerak",
      "char": 10,
      "skin": false,
      "area": 3,
      "subarea": 3,
      "loops": 0,
      "wep": 71,
      "bwep": 6,
      "win": false,
      "kills": 81,
      "ultra": 0,
      "skills": [
        8,
        12
      ],
      "crown": 1,
      "version": 2616,
      "uid": "wMoFZw0K728rw20",
      "runId": 663081683
    },
    "a576y2Tg2GA2cZp": {
      "name": "TheGuy",
      "char": 6,
      "skin": false,
      "area": 3,
      "subarea": 2,
      "loops": 0,
      "wep": 13,
      "bwep": 21,
      "win": false,
      "kills": 94,
      "ultra": 0,
      "skills": [
        8,
        26
      ],
      "crown": 1,
      "version": 2616,
      "uid": "a576y2Tg2GA2cZp",
      "runId": 663081683
    },
    "93z65lvxbCGUxaT": {
      "name": "moises",
      "char": 5,
      "skin": false,
      "area": 101,
      "subarea": 1,
      "loops": 0,
      "wep": 69,
      "bwep": 21,
      "win": false,
      "kills": 28,
      "ultra": 0,
      "skills": [
        25
      ],
      "crown": 1,
      "version": 2616,
      "uid": "93z65lvxbCGUxaT",
      "runId": 663081683
    },
    "ZfuO08B9l8h00f5": {
      "name": "Лагающий2009",
      "char": 7,
      "skin": true,
      "area": 1,
      "subarea": 3,
      "loops": 0,
      "wep": 21,
      "bwep": 1,
      "win": false,
      "kills": 35,
      "ultra": 0,
      "skills": [],
      "crown": 1,
      "version": 2616,
      "uid": "ZfuO08B9l8h00f5",
      "runId": 663081683
    },
    "399lza28rrvH7f7": {
      "name": "Throne",
      "char": 2,
      "skin": false,
      "area": 3,
      "subarea": 1,
      "loops": 0,
      "wep": 21,
      "bwep": 27,
      "win": false,
      "kills": 81,
      "ultra": 0,
      "skills": [
        25,
        8,
        4
      ],
      "crown": 1,
      "version": 2616,
      "uid": "399lza28rrvH7f7",
      "runId": 663081683
    }
  }
}