{
  "day": 14,
  "entries": {
    "cE6W3fvh74w6VRA": {
      "name": "coco33",
      "char": 12,
      "skin": false,
      "area": 1,
      "subarea": 1,
      "loops": 0,
      "wep": 81,
      "bwep": 0,
      "win": false,
      "kills": 0,
      "crown": 1,
      "version": 2616,
      "uid": "cE6W3fvh74w6VRA",
      "runId": 300957555
    },
    "B8Tn39uyKxeizOn": {
      "name": "SEBITAXXD",
      "char": 2,
      "skin": false,
      "area": 3,
      "subarea": 2,
      "loops": 0,
      "wep": 5,
      "bwep": 31,
      "win": false,
      "kills": 96,
      "ultra": 0,
      "skills": [
        7,
        10,
        16
      ],
      "crown": 1,
      "version": 2616,
      "uid": "B8Tn39uyKxeizOn",
      "runId": 300957555
    },
    "322i9OEnYPbgt6y": {
      "name": "Rafa",
      "char": 2,
      "skin": false,
      "area": 2,
      "subarea": 1,
      "loops": 0,
      "wep": 18,
      "bwep": 1,
      "win": false,
      "kills": 52,
      "ultra": 0,
      "skills": [
        7,
        10
      ],
      "crown": 1,
      "version": 2616,
      "uid": "322i9OEnYPbgt6y",
      "runId": 300957555
    },
    "8q5fG405p47SjK1": {
      "name": "teetrone",
      "char": 2,
      "skin": false,
      "area": 1,
      "subarea": 3,
      "loops": 0,
      "wep": 5,
      "bwep": 3,
      "win": false,
      "kills": 44,
      "ultra": 0,
      "skills": [
        7
      ],
      "crown": 1,
      "version": 2616,
      "uid": "8q5fG405p47SjK1",
      "runId": 300957555
    },
    "UdVFduPKTKPQPSz": {
      "name": "Oigrestoriop",
      "char": 7,
      "skin": true,
      "area": 2,
      "subarea": 1,
      "loops": 0,
      "wep": 69,
      "bwep": 5,
      "win": false,
      "kills": 52,
      "ultra": 0,
      "skills": [
        14,
        17
      ],
      "crown": 1,
      "version": 2616,
      "uid": "UdVFduPKTKPQPSz",
      "runId": 300957555
    },
    "i08X5ClmmEPc8ZC": {
      "name": "Aleee",
      "char": 6,
      "skin": false,
      "area": 1,
      "subarea": 3,
      "loops": 0,
      "wep": 5,
      "bwep": 39,
      "win": false,
      "kills": 43,
      "ultra": 0,
      "skills": [
        7
      ],
      "crown": 1,
      "version": 2616,
      "uid": "i08X5ClmmEPc8ZC",
      "runId": 300957555
    },
    "RuBP3cv5esn30I4": {
      "name": "Bub",
      "char": 11,
      "skin": false,
      "area": 1,
      "subarea": 3,
      "loops": 0,
      "wep": 5,
      "bwep": 1,
      "win": false,
      "kills": 33,
      "ultra": 0,
      "skills": [
        23
      ],
      "crown": 1,
      "version": 2616,
      "uid": "RuBP3cv5esn30I4",
      "runId": 300957555
    },
    "M4463L5j78lwMa2": {
      "name": "DaRELFinklDnkle",
      "char": 14,
      "skin": false,
      "area": 1,
      "subarea": 1,
      "loops": 1,
      "wep": 33,
      "bwep": 105,
      "win": false,
      "kills": 437,
      "ultra": 0,
      "skills": [
        7,
        21,
        27,
        24,
        16,
        2,
        14,
        4
      ],
      "crown": 11,
      "version": 2616,
      "uid": "M4463L5j78lwMa2",
      "runId": 300957555
    },
    "36lyg6gDZf31lew": {
      "name": "Seeker4",
      "char": 2,
      "skin": false,
      "area": 1,
      "subarea": 2,
      "loops": 0,
      "wep": 5,
      "bwep": 1,
      "win": false,
      "kills": 18,
      "crown": 1,
      "version": 2616,
      "uid": "36lyg6gDZf31lew",
      "runId": 300957555
    },
    "0W5h81S2jBC66p5": {
      "name": "EverLoop",
      "char": 14,
      "skin": false,
      "area": 1,
      "subarea": 1,
      "loops": 0,
      "wep": 56,
      "bwep": 5,
      "win": false,
      "kills": 6,
      "crown": 1,
      "version": 2616,
      "uid": "0W5h81S2jBC66p5",
      "runId": 300957555
    },
    "7UjeSnnc07ij35o": {
      "name": "GHOST",
      "char": 11,
      "skin": false,
      "area": 3,
      "subarea": 1,
      "loops": 0,
      "wep": 17,
      "bwep": 5,
      "win": false,
      "kills": 79,
      "ultra": 0,
      "skills": [
        10
      ],
      "crown": 1,
      "version": 2616,
      "uid": "7UjeSnnc07ij35o",
      "runId": 300957555
    },
    "277CYJpZa4NVwDf": {
      "name": "felix",
      "char": 8,
      "skin": false,
      "area": 103,
      "subarea": 1,
      "loops": 0,
      "wep": 71,
      "bwep": 0,
      "win": false,
      "kills": 85,
      "ultra": 0,
      "skills": [
        7,
        14,
        27
      ],
      "crown": 1,
      "version": 2616,
      "uid": "277CYJpZa4NVwDf",
      "runId": 300957555
    }
  }
}