{
  "day": 14,
  "entries": {
    "Wq0wIvmZc5K4d6m": {
      "name": "elhombrejhoniel",
      "char": 2,
      "skin": false,
      "area": 0,
      "subarea": 1,
      "loops": 2,
      "wep": 11,
      "bwep": 95,
      "win": false,
      "kills": 1340,
      "ultra": 1,
      "skills": [
        4,
        8,
        25,
        7,
        6,
        27,
        24,
        16
      ],
      "crown": 7,
      "version": 2616,
      "uid": "Wq0wIvmZc5K4d6m",
      "runId": 779953462
    },
    "81R77D57o5dkajM": {
      "name": "NumbraMani",
      "char": 8,
      "skin": false,
      "area": 2,
      "subarea": 1,
      "loops": 0,
      "wep": 30,
      "bwep": 27,
      "win": false,
      "kills": 73,
      "ultra": 0,
      "skills": [
        4,
        19
      ],
      "crown": 1,
      "version": 2616,
      "uid": "81R77D57o5dkajM",
      "runId": 779953462
    },
    "gwe4067EMKKPcxt": {
      "name": "Ripneck",
      "char": 8,
      "skin": false,
      "area": 1,
      "subarea": 3,
      "loops": 0,
      "wep": 34,
      "bwep": 17,
      "win": false,
      "kills": 30,
      "ultra": 0,
      "skills": [
        3
      ],
      "crown": 1,
      "version": 2616,
      "uid": "gwe4067EMKKPcxt",
      "runId": 779953462
    },
    "8fysVtdREdlxp57": {
      "name": "HIR",
      "char": 2,
      "skin": false,
      "area": 1,
      "subarea": 3,
      "loops": 0,
      "wep": 27,
      "bwep": 17,
      "win": false,
      "kills": 46,
      "ultra": 0,
      "skills": [
        12
      ],
      "crown": 1,
      "version": 2616,
      "uid": "8fysVtdREdlxp57",
      "runId": 779953462
    },
    "H5dV645bca27OVy": {
      "name": "Матвей",
      "char": 7,
      "skin": false,
      "area": 2,
      "subarea": 1,
      "loops": 0,
      "wep": 1,
      "bwep": 1,
      "win": false,
      "kills": 55,
      "ultra": 0,
      "skills": [
        4,
        12
      ],
      "crown": 1,
      "version": 2616,
      "uid": "H5dV645bca27OVy",
      "runId": 779953462
    },
    "Hh22qMg7J30iO4B": {
      "name": "Hungg",
      "char": 8,
      "skin": false,
      "area": 2,
      "subarea": 1,
      "loops": 0,
      "wep": 88,
      "bwep": 16,
      "win": false,
      "kills": 48,
      "ultra": 0,
      "skills": [
        4,
        19
      ],
      "crown": 1,
      "version": 2616,
      "uid": "Hh22qMg7J30iO4B",
      "runId": 779953462
    },
    "Ry52m4OB749lCe3": {
      "name": "Fake",
      "char": 2,
      "skin": true,
      "area": 4,
      "subarea": 1,
      "loops": 0,
      "wep": 58,
      "bwep": 62,
      "win": false,
      "kills": 174,
      "ultra": 0,
      "skills": [
        3,
        27,
        25,
        22
      ],
      "crown": 11,
      "version": 2616,
      "uid": "Ry52m4OB749lCe3",
      "runId": 779953462
    },
    "gM3527CPzcTPqKo": {
      "name": "Rhythm",
      "char": 2,
      "skin": true,
      "area": 1,
      "subarea": 3,
      "loops": 0,
      "wep": 5,
      "bwep": 1,
      "win": false,
      "kills": 45,
      "ultra": 0,
      "skills": [
        4
      ],
      "crown": 1,
      "version": 2616,
      "uid": "gM3527CPzcTPqKo",
      "runId": 779953462
    },
    "M3q90bnZ7zzqN14": {
      "name": "я_это_я",
      "char": 11,
      "skin": false,
      "area": 7,
      "subarea": 3,
      "loops": 0,
      "wep": 12,
      "bwep": 74,
      "win": false,
      "kills": 319,
      "ultra": 0,
      "skills": [
        3,
        14,
        8,
        25,
        4,
        9,
        13,
        17
      ],
      "crown": 1,
      "version": 2616,
      "uid": "M3q90bnZ7zzqN14",
      "runId": 779953462
    },
    "539n3jLTPf84f5a": {
      "name": "Byeehana",
      "char": 4,
      "skin": false,
      "area": 3,
      "subarea": 2,
      "loops": 0,
      "wep": 5,
      "bwep": 34,
      "win": false,
      "kills": 141,
      "ultra": 0,
      "skills": [
        4,
        25
      ],
      "crown": 1,
      "version": 2616,
      "uid": "539n3jLTPf84f5a",
      "runId": 779953462
    },
    "veNM445KoAqLS4N": {
      "name": "Тобепизда",
      "char": 2,
      "skin": false,
      "area": 1,
      "subarea": 3,
      "loops": 0,
      "wep": 3,
      "bwep": 1,
      "win": false,
      "kills": 32,
      "ultra": 0,
      "skills": [
        12
      ],
      "crown": 1,
      "version": 2616,
      "uid": "veNM445KoAqLS4N",
      "runId": 779953462
    },
    "90cnT135q0TE0q2": {
      "name": "Holop(фюрер",
      "char": 2,
      "skin": true,
      "area": 2,
      "subarea": 1,
      "loops": 0,
      "wep": 71,
      "bwep": 5,
      "win": false,
      "kills": 63,
      "ultra": 0,
      "skills": [
        4,
        12
      ],
      "crown": 1,
      "version": 2616,
      "uid": "90cnT135q0TE0q2",
      "runId": 779953462
    },
    "5gU7s7keHa8O3p0": {
      "name": "Rj",
      "char": 10,
      "skin": false,
      "area": 1,
      "subarea": 3,
      "loops": 0,
      "wep": 27,
      "bwep": 1,
      "win": false,
      "kills": 37,
      "ultra": 0,
      "skills": [
        4
      ],
      "crown": 1,
      "version": 2616,
      "uid": "5gU7s7keHa8O3p0",
      "runId": 779953462
    },
    "SUHjzq21OSG518m": {
      "name": "Seeker9031",
      "char": 3,
      "skin": false,
      "area": 2,
      "subarea": 1,
      "loops": 0,
      "wep": 30,
      "bwep": 7,
      "win": false,
      "kills": 69,
      "ultra": 0,
      "skills": [
        4
      ],
      "crown": 1,
      "version": 2616,
      "uid": "SUHjzq21OSG518m",
      "runId": 779953462
    },
    "h8sHiX34isDPi5l": {
      "name": "SKILL_ISSUE",
      "char": 10,
      "skin": true,
      "area": 1,
      "subarea": 3,
      "loops": 1,
      "wep": 63,
      "bwep": 107,
      "win": false,
      "kills": 575,
      "ultra": 2,
      "skills": [
        3,
        27,
        25,
        7,
        4,
        9,
        22
      ],
      "crown": 1,
      "version": 2616,
      "uid": "h8sHiX34isDPi5l",
      "runId": 779953462
    },
    "rI0Vr19z1vXI4vN": {
      "name": "Silos",
      "char": 4,
      "skin": true,
      "area": 1,
      "subarea": 3,
      "loops": 0,
      "wep": 1,
      "bwep": 21,
      "win": false,
      "kills": 48,
      "ultra": 0,
      "skills": [
        3,
        2
      ],
      "crown": 1,
      "version": 2616,
      "uid": "rI0Vr19z1vXI4vN",
      "runId": 779953462
    },
    "bpa1O1p16Br2s0o": {
      "name": "angru",
      "char": 2,
      "skin": false,
      "area": 5,
      "subarea": 3,
      "loops": 0,
      "wep": 17,
      "bwep": 5,
      "win": false,
      "kills": 246,
      "ultra": 0,
      "skills": [
        4,
        27,
        25,
        6,
        9
      ],
      "crown": 1,
      "version": 2616,
      "uid": "bpa1O1p16Br2s0o",
      "runId": 779953462
    },
    "CM312LhJ9lrKk0s": {
      "name": "zaqmad",
      "char": 1,
      "skin": false,
      "area": 103,
      "subarea": 1,
      "loops": 0,
      "wep": 117,
      "bwep": 43,
      "win": false,
      "kills": 135,
      "ultra": 0,
      "skills": [
        4,
        12,
        16
      ],
      "crown": 1,
      "version": 2616,
      "uid": "CM312LhJ9lrKk0s",
      "runId": 779953462
    },
    "cqQi717F3j8va9a": {
      "name": "Zahnesfall",
      "char": 4,
      "skin": false,
      "area": 1,
      "subarea": 2,
      "loops": 0,
      "wep": 7,
      "bwep": 17,
      "win": false,
      "kills": 22,
      "ultra": 0,
      "skills": [
        4
      ],
      "crown": 1,
      "version": 2616,
      "uid": "cqQi717F3j8va9a",
      "runId": 779953462
    },
    "mQ6dxSp1osVs2vM": {
      "name": "souvlaki",
      "char": 9,
      "skin": false,
      "area": 2,
      "subarea": 1,
      "loops": 0,
      "wep": 46,
      "bwep": 5,
      "win": false,
      "kills": 60,
      "ultra": 0,
      "skills": [
        12,
        19
      ],
      "crown": 1,
      "version": 2616,
      "uid": "mQ6dxSp1osVs2vM",
      "runId": 779953462
    },
    "EVl3A0wZ9bTFs7w": {
      "name": "Attreu",
      "char": 8,
      "skin": true,
      "area": 2,
      "subarea": 1,
      "loops": 0,
      "wep": 3,
      "bwep": 16,
      "win": false,
      "kills": 71,
      "ultra": 0,
      "skills": [
        4,
        12
      ],
      "crown": 1,
      "version": 2616,
      "uid": "EVl3A0wZ9bTFs7w",
      "runId": 779953462
    },
    "p6KHvaIIKk6110B": {
      "name": "zooooo",
      "char": 2,
      "skin": false,
      "area": 3,
      "subarea": 1,
      "loops": 0,
      "wep": 75,
      "bwep": 1,
      "win": false,
      "kills": 81,
      "ultra": 0,
      "skills": [
        12,
        2,
        8
      ],
      "crown": 1,
      "version": 2616,
      "uid": "p6KHvaIIKk6110B",
      "runId": 779953462
    },
    "JJouI9UBh20EpoB": {
      "name": "Yordy",
      "char": 8,
      "skin": true,
      "area": 3,
      "subarea": 3,
      "loops": 0,
      "wep": 8,
      "bwep": 57,
      "win": false,
      "kills": 144,
      "ultra": 0,
      "skills": [
        3,
        2,
        8,
        25
      ],
      "crown": 1,
      "version": 2616,
      "uid": "JJouI9UBh20EpoB",
      "runId": 779953462
    },
    "uMB9Yq0732UxVF9": {
      "name": "пидор",
      "char": 4,
      "skin": false,
      "area": 1,
      "subarea": 1,
      "loops": 0,
      "wep": 1,
      "bwep": 5,
      "win": false,
      "kills": 8,
      "crown": 1,
      "version": 2616,
      "uid": "uMB9Yq0732UxVF9",
      "runId": 779953462
    },
    "McmC2g0Ib40dUdn": {
      "name": "rcat",
      "char": 4,
      "skin": false,
      "area": 1,
      "subarea": 2,
      "loops": 0,
      "wep": 1,
      "bwep": 5,
      "win": false,
      "kills": 20,
      "ultra": 0,
      "skills": [
        4
      ],
      "crown": 1,
      "version": 2616,
      "uid": "McmC2g0Ib40dUdn",
      "runId": 779953462
    },
    "w20B0r75eP2CtnB": {
      "name": "piskunchik",
      "char": 2,
      "skin": true,
      "area": 7,
      "subarea": 2,
      "loops": 1,
      "wep": 96,
      "bwep": 60,
      "win": false,
      "kills": 1238,
      "ultra": 1,
      "skills": [
        19,
        8,
        22,
        4,
        27,
        2,
        25
      ],
      "crown": 1,
      "version": 2616,
      "uid": "w20B0r75eP2CtnB",
      "runId": 779953462
    },
    "7m6rMl97DPjVY5B": {
      "name": "1234",
      "char": 6,
      "skin": false,
      "area": 1,
      "subarea": 1,
      "loops": 0,
      "wep": 39,
      "bwep": 0,
      "win": false,
      "kills": 3,
      "crown": 1,
      "version": 2616,
      "uid": "7m6rMl97DPjVY5B",
      "runId": 779953462
    },
    "e5IWbVh9uU3A639": {
      "name": "ROLAND",
      "char": 2,
      "skin": true,
      "area": 3,
      "subarea": 3,
      "loops": 1,
      "wep": 105,
      "bwep": 106,
      "win": false,
      "kills": 1110,
      "ultra": 1,
      "skills": [
        4,
        12,
        27,
        25,
        23,
        9,
        26,
        16
      ],
      "crown": 7,
      "version": 2616,
      "uid": "e5IWbVh9uU3A639",
      "runId": 779953462
    },
    "307Mga56XPNyUsO": {
      "name": "GraagraGreuu",
      "char": 2,
      "skin": false,
      "area": 1,
      "subarea": 3,
      "loops": 0,
      "wep": 71,
      "bwep": 6,
      "win": false,
      "kills": 37,
      "ultra": 0,
      "skills": [
        4
      ],
      "crown": 1,
      "version": 2616,
      "uid": "307Mga56XPNyUsO",
      "runId": 779953462
    },
    "u1oFU0aHFKh696I": {
      "name": "Митяй2009",
      "char": 7,
      "skin": false,
      "area": 3,
      "subarea": 3,
      "loops": 0,
      "wep": 71,
      "bwep": 1,
      "win": false,
      "kills": 143,
      "ultra": 0,
      "skills": [
        4,
        19,
        16,
        25,
        13
      ],
      "crown": 5,
      "version": 2616,
      "uid": "u1oFU0aHFKh696I",
      "runId": 779953462
    },
    "edhTZ83F85f2l9U": {
      "name": "friezed228",
      "char": 2,
      "skin": false,
      "area": 2,
      "subarea": 1,
      "loops": 0,
      "wep": 5,
      "bwep": 3,
      "win": false,
      "kills": 74,
      "ultra": 0,
      "skills": [
        4,
        2
      ],
      "crown": 1,
      "version": 2616,
      "uid": "edhTZ83F85f2l9U",
      "runId": 779953462
    }
  }
}