{
  "day": 17,
  "entries": {
    "g76z78LjOTdhCfi": {
      "name": "Stal",
      "char": 10,
      "skin": false,
      "area": 5,
      "subarea": 3,
      "loops": 0,
      "wep": 89,
      "bwep": 75,
      "win": false,
      "kills": 291,
      "ultra": 0,
      "skills": [
        1,
        23,
        16,
        10,
        27,
        8,
        13
      ],
      "crown": 1,
      "version": 2616,
      "uid": "g76z78LjOTdhCfi",
      "runId": 978272039
    },
    "EVl3A0wZ9bTFs7w": {
      "name": "Attreu",
      "char": 6,
      "skin": true,
      "area": 7,
      "subarea": 3,
      "loops": 1,
      "wep": 74,
      "bwep": 93,
      "win": false,
      "kills": 1272,
      "ultra": 1,
      "skills": [
        1,
        25,
        23,
        9,
        27,
        8,
        13
      ],
      "crown": 1,
      "version": 2616,
      "uid": "EVl3A0wZ9bTFs7w",
      "runId": 978272039
    },
    "07G6h6Y87K3t72h": {
      "name": "roronoa",
      "char": 4,
      "skin": false,
      "area": 1,
      "subarea": 1,
      "loops": 0,
      "wep": 1,
      "bwep": 0,
      "win": false,
      "kills": 5,
      "crown": 1,
      "version": 2616,
      "uid": "07G6h6Y87K3t72h",
      "runId": 978272039
    },
    "2lJ2YMZrzyJGmI6": {
      "name": "ian",
      "char": 1,
      "skin": false,
      "area": 2,
      "subarea": 1,
      "loops": 0,
      "wep": 23,
      "bwep": 6,
      "win": false,
      "kills": 111,
      "ultra": 0,
      "skills": [
        1,
        6,
        9
      ],
      "crown": 1,
      "version": 2616,
      "uid": "2lJ2YMZrzyJGmI6",
      "runId": 978272039
    },
    "O82eCuRSbf655d3": {
      "name": "Andersony",
      "char": 4,
      "skin": false,
      "area": 1,
      "subarea": 1,
      "loops": 0,
      "wep": 5,
      "bwep": 1,
      "win": false,
      "kills": 9,
      "crown": 1,
      "version": 2616,
      "uid": "O82eCuRSbf655d3",
      "runId": 978272039
    },
    "EyivYO7HV1WHL1v": {
      "name": "lol8",
      "char": 4,
      "skin": false,
      "area": 1,
      "subarea": 1,
      "loops": 0,
      "wep": 1,
      "bwep": 0,
      "win": false,
      "kills": 3,
      "crown": 1,
      "version": 2616,
      "uid": "EyivYO7HV1WHL1v",
      "runId": 978272039
    }
  }
}