{
  "day": 1,
  "entries": {
    "p1jD4CJGdLtt2U2": {
      "name": "afganistano999",
      "char": 8,
      "skin": true,
      "area": 5,
      "subarea": 3,
      "loops": 0,
      "wep": 14,
      "bwep": 20,
      "win": false,
      "kills": 230,
      "ultra": 0,
      "skills": [
        8,
        28,
        1,
        14,
        9,
        27
      ],
      "crown": 1,
      "version": 2616,
      "uid": "p1jD4CJGdLtt2U2",
      "runId": 836427672
    },
    "ab25r4ETlL2Myj6": {
      "name": "ЕбалЖаб...",
      "char": 5,
      "skin": false,
      "area": 1,
      "subarea": 2,
      "loops": 0,
      "wep": 1,
      "bwep": 27,
      "win": false,
      "kills": 9,
      "ultra": 0,
      "skills": [
        25
      ],
      "crown": 1,
      "version": 2616,
      "uid": "ab25r4ETlL2Myj6",
      "runId": 836427672
    },
    "Y7L88XBgLHkN4lC": {
      "name": "Havoc",
      "char": 8,
      "skin": true,
      "area": 5,
      "subarea": 3,
      "loops": 0,
      "wep": 107,
      "bwep": 76,
      "win": false,
      "kills": 218,
      "ultra": 0,
      "skills": [
        8,
        28,
        4,
        9,
        27
      ],
      "crown": 1,
      "version": 2616,
      "uid": "Y7L88XBgLHkN4lC",
      "runId": 836427672
    },
    "Spo2m66764o2WtO": {
      "name": "Z3zima",
      "char": 4,
      "skin": false,
      "area": 3,
      "subarea": 2,
      "loops": 0,
      "wep": 17,
      "bwep": 38,
      "win": false,
      "kills": 111,
      "ultra": 0,
      "skills": [
        8,
        12,
        1,
        14
      ],
      "crown": 1,
      "version": 2616,
      "uid": "Spo2m66764o2WtO",
      "runId": 836427672
    },
    "W471611Hz3mp7zD": {
      "name": "xxx",
      "char": 5,
      "skin": false,
      "area": 3,
      "subarea": 1,
      "loops": 0,
      "wep": 5,
      "bwep": 50,
      "win": false,
      "kills": 89,
      "ultra": 0,
      "skills": [
        8,
        12,
        1
      ],
      "crown": 1,
      "version": 2616,
      "uid": "W471611Hz3mp7zD",
      "runId": 836427672
    },
    "Ry52m4OB749lCe3": {
      "name": "Fake",
      "char": 12,
      "skin": false,
      "area": 2,
      "subarea": 1,
      "loops": 0,
      "wep": 18,
      "bwep": 81,
      "win": false,
      "kills": 61,
      "ultra": 0,
      "skills": [
        25,
        21
      ],
      "crown": 1,
      "version": 2616,
      "uid": "Ry52m4OB749lCe3",
      "runId": 836427672
    },
    "70U9wJO1YQv91LZ": {
      "name": "IanAarón",
      "char": 2,
      "skin": false,
      "area": 5,
      "subarea": 3,
      "loops": 0,
      "wep": 114,
      "bwep": 89,
      "win": false,
      "kills": 231,
      "ultra": 0,
      "skills": [
        8,
        12,
        1,
        23,
        4,
        28
      ],
      "crown": 1,
      "version": 2616,
      "uid": "70U9wJO1YQv91LZ",
      "runId": 836427672
    },
    "w20B0r75eP2CtnB": {
      "name": "piskunchik",
      "char": 4,
      "skin": false,
      "area": 2,
      "subarea": 1,
      "loops": 0,
      "wep": 23,
      "bwep": 3,
      "win": false,
      "kills": 72,
      "ultra": 0,
      "skills": [
        8,
        28,
        14
      ],
      "crown": 1,
      "version": 2616,
      "uid": "w20B0r75eP2CtnB",
      "runId": 836427672
    },
    "H5dV645bca27OVy": {
      "name": "Матвей",
      "char": 1,
      "skin": false,
      "area": 1,
      "subarea": 2,
      "loops": 0,
      "wep": 3,
      "bwep": 1,
      "win": false,
      "kills": 21,
      "ultra": 0,
      "skills": [
        25
      ],
      "crown": 1,
      "version": 2616,
      "uid": "H5dV645bca27OVy",
      "runId": 836427672
    },
    "76Qg6Bhk4tt9ZCq": {
      "name": "Bishopbelcebu",
      "char": 1,
      "skin": false,
      "area": 1,
      "subarea": 2,
      "loops": 0,
      "wep": 27,
      "bwep": 1,
      "win": false,
      "kills": 18,
      "ultra": 0,
      "skills": [
        2
      ],
      "crown": 1,
      "version": 2616,
      "uid": "76Qg6Bhk4tt9ZCq",
      "runId": 836427672
    }
  }
}