{
  "seed": 621230677,
  "entries": {
    "P48as3Q3rUCnIk5": {
      "name": "Cruzadosxd111",
      "char": 3,
      "skin": false,
      "area": 104,
      "subarea": 1,
      "loops": 0,
      "wep": 8,
      "bwep": 41,
      "win": false,
      "kills": 160,
      "ultra": 0,
      "skills": [
        1,
        27,
        7
      ],
      "crown": 11,
      "version": 2616,
      "uid": "P48as3Q3rUCnIk5",
      "runId": 621230677
    },
    "6DKP2Whp9p86Xnu": {
      "name": "AlFaZ_ToP",
      "char": 3,
      "skin": false,
      "area": 104,
      "subarea": 1,
      "loops": 0,
      "wep": 116,
      "bwep": 10,
      "win": false,
      "kills": 169,
      "ultra": 0,
      "skills": [
        8,
        7,
        9,
        27,
        16
      ],
      "crown": 11,
      "version": 2616,
      "uid": "6DKP2Whp9p86Xnu",
      "runId": 621230677
    },
    "2gc1fF0klt0YrI4": {
      "name": "неономизация",
      "char": 3,
      "skin": false,
      "area": 104,
      "subarea": 1,
      "loops": 0,
      "wep": 23,
      "bwep": 13,
      "win": false,
      "kills": 203,
      "ultra": 0,
      "skills": [
        13,
        23,
        22,
        1
      ],
      "crown": 11,
      "version": 2616,
      "uid": "2gc1fF0klt0YrI4",
      "runId": 621230677
    },
    "5L1T3QQyOsK5DA2": {
      "name": "Rasuki",
      "char": 3,
      "skin": false,
      "area": 3,
      "subarea": 2,
      "loops": 0,
      "wep": 76,
      "bwep": 38,
      "win": false,
      "kills": 121,
      "ultra": 0,
      "skills": [
        8,
        1,
        4
      ],
      "crown": 11,
      "version": 2616,
      "uid": "5L1T3QQyOsK5DA2",
      "runId": 621230677
    }
  }
}