{
  "seed": 2082790893,
  "entries": {
    "C2dR3t6EC5o9LN5": {
      "name": "Shion",
      "char": 5,
      "skin": false,
      "area": 3,
      "subarea": 1,
      "loops": 0,
      "wep": 8,
      "bwep": 4,
      "win": false,
      "kills": 158,
      "ultra": 0,
      "skills": [
        9,
        7,
        3
      ],
      "crown": 7,
      "version": 2616,
      "uid": "C2dR3t6EC5o9LN5",
      "runId": 2082790893
    },
    "730vnjh2Fy89dtn": {
      "name": "Aboba",
      "char": 4,
      "skin": false,
      "area": 2,
      "subarea": 1,
      "loops": 0,
      "wep": 27,
      "bwep": 61,
      "win": false,
      "kills": 159,
      "ultra": 0,
      "skills": [
        6,
        12,
        2
      ],
      "crown": 7,
      "version": 2616,
      "uid": "730vnjh2Fy89dtn",
      "runId": 2082790893
    },
    "mzZl1yf8k410ct2": {
      "name": "Seeker90",
      "char": 4,
      "skin": false,
      "area": 2,
      "subarea": 1,
      "loops": 0,
      "wep": 61,
      "bwep": 0,
      "win": false,
      "kills": 114,
      "ultra": 0,
      "skills": [
        6,
        12,
        3
      ],
      "crown": 7,
      "version": 2616,
      "uid": "mzZl1yf8k410ct2",
      "runId": 2082790893
    }
  }
}